bluecore_models/bluecore_graph.py
bluecore_models/namespaces.py
bluecore_models/models/__init__.py
bluecore_models/models/base.py
bluecore_models/models/bf_classes.py
bluecore_models/models/instance.py
bluecore_models/models/other_resource.py
bluecore_models/models/resource.py
bluecore_models/models/version.py
bluecore_models/models/work.py
bluecore_models/utils/db.py
bluecore_models/utils/graph.py
bluecore_models/utils/vector_db.py
bluecore_models-0.10.2.dist-info/METADATA
bluecore_models-0.10.2.dist-info/WHEEL
bluecore_models-0.10.2.dist-info/licenses/LICENSE
bluecore_models-0.10.2.dist-info/RECORD
