Metadata-Version: 2.4
Name: bluecore-models
Version: 0.10.2
Summary: Blue Core BIBFRAME Data Models
License-File: LICENSE
Requires-Python: >=3.12
Requires-Dist: alembic>=1.14.1
Requires-Dist: psycopg2-binary>=2.9.10
Requires-Dist: pyld>=2.0.4
Requires-Dist: pymilvus[model]>=2.5.12
Requires-Dist: rdflib>=7.1.3
